{
  "seed": 409,
  "configPath": "C:\\WS\\WorldSimulation10028\\data\\sim_config.toml",
  "configHash": "7890ecde6692423c",
  "startYear": -5000,
  "endYear": 2025,
  "stoppedOnTargetTech": false,
  "stoppedOnTargetTechYear": null,
  "worldStartYear": -5000,
  "useGPU": false,
  "stateDiagnostics": true,
  "total_score": 0.0,
  "gates": {
    "metric_availability": true,
    "canary_pass": false,
    "backend_parity_pass": false,
    "hardfail": ""
  },
  "top_violations": [],
  "invariants": {
    "ok": true,
    "message": ""
  },
  "checkpoints": [
    {
      "year": -5000,
      "world_pop_total": 23811606.000000,
      "world_food_adequacy_index": 0.999389,
      "world_trade_intensity": 0.001377,
      "world_urban_share_proxy": 0.024309,
      "world_tech_capability_index_median": 0.280134,
      "world_state_capacity_index_median": 0.667798,
      "major_war_count": 0.000000,
      "famine_wave_count": 0,
      "epidemic_wave_count": 0,
      "migration_rate_t": 0.030385
    },
    {
      "year": -4950,
      "world_pop_total": 30301529.000000,
      "world_food_adequacy_index": 0.940527,
      "world_trade_intensity": 0.000000,
      "world_urban_share_proxy": 0.023093,
      "world_tech_capability_index_median": 0.289372,
      "world_state_capacity_index_median": 0.877101,
      "major_war_count": 0.000901,
      "famine_wave_count": 49,
      "epidemic_wave_count": 0,
      "migration_rate_t": 0.059473
    },
    {
      "year": -4900,
      "world_pop_total": 34766456.000000,
      "world_food_adequacy_index": 0.945359,
      "world_trade_intensity": 0.000784,
      "world_urban_share_proxy": 0.023306,
      "world_tech_capability_index_median": 0.299164,
      "world_state_capacity_index_median": 0.878283,
      "major_war_count": 0.000950,
      "famine_wave_count": 77,
      "epidemic_wave_count": 0,
      "migration_rate_t": 0.054641
    },
    {
      "year": -4850,
      "world_pop_total": 39264098.000000,
      "world_food_adequacy_index": 0.960181,
      "world_trade_intensity": 0.000415,
      "world_urban_share_proxy": 0.023731,
      "world_tech_capability_index_median": 0.310135,
      "world_state_capacity_index_median": 0.884587,
      "major_war_count": 0.000782,
      "famine_wave_count": 66,
      "epidemic_wave_count": 0,
      "migration_rate_t": 0.039819
    },
    {
      "year": -4800,
      "world_pop_total": 44205068.000000,
      "world_food_adequacy_index": 0.980686,
      "world_trade_intensity": 0.000804,
      "world_urban_share_proxy": 0.024033,
      "world_tech_capability_index_median": 0.321503,
      "world_state_capacity_index_median": 0.888192,
      "major_war_count": 0.000427,
      "famine_wave_count": 66,
      "epidemic_wave_count": 0,
      "migration_rate_t": 0.019314
    },
    {
      "year": -4750,
      "world_pop_total": 49683262.000000,
      "world_food_adequacy_index": 0.987364,
      "world_trade_intensity": 0.000000,
      "world_urban_share_proxy": 0.024270,
      "world_tech_capability_index_median": 0.333318,
      "world_state_capacity_index_median": 0.889907,
      "major_war_count": 0.000314,
      "famine_wave_count": 59,
      "epidemic_wave_count": 0,
      "migration_rate_t": 0.012636
    },
    {
      "year": -4700,
      "world_pop_total": 55508031.000000,
      "world_food_adequacy_index": 0.976842,
      "world_trade_intensity": 0.000845,
      "world_urban_share_proxy": 0.024505,
      "world_tech_capability_index_median": 0.344112,
      "world_state_capacity_index_median": 0.889950,
      "major_war_count": 0.000643,
      "famine_wave_count": 83,
      "epidemic_wave_count": 0,
      "migration_rate_t": 0.023158
    },
    {
      "year": -4650,
      "world_pop_total": 62067238.000000,
      "world_food_adequacy_index": 0.984253,
      "world_trade_intensity": 0.000604,
      "world_urban_share_proxy": 0.024746,
      "world_tech_capability_index_median": 0.356568,
      "world_state_capacity_index_median": 0.890191,
      "major_war_count": 0.000489,
      "famine_wave_count": 76,
      "epidemic_wave_count": 0,
      "migration_rate_t": 0.015747
    },
    {
      "year": -4600,
      "world_pop_total": 69366302.000000,
      "world_food_adequacy_index": 0.989537,
      "world_trade_intensity": 0.000771,
      "world_urban_share_proxy": 0.025358,
      "world_tech_capability_index_median": 0.369489,
      "world_state_capacity_index_median": 0.890821,
      "major_war_count": 0.000363,
      "famine_wave_count": 88,
      "epidemic_wave_count": 0,
      "migration_rate_t": 0.010463
    },
    {
      "year": -4550,
      "world_pop_total": 76695150.000000,
      "world_food_adequacy_index": 0.991395,
      "world_trade_intensity": 0.000797,
      "world_urban_share_proxy": 0.025682,
      "world_tech_capability_index_median": 0.382566,
      "world_state_capacity_index_median": 0.891339,
      "major_war_count": 0.000330,
      "famine_wave_count": 118,
      "epidemic_wave_count": 0,
      "migration_rate_t": 0.008605
    },
    {
      "year": -4500,
      "world_pop_total": 84392015.000000,
      "world_food_adequacy_index": 0.996421,
      "world_trade_intensity": 0.000811,
      "world_urban_share_proxy": 0.026125,
      "world_tech_capability_index_median": 0.395549,
      "world_state_capacity_index_median": 0.891049,
      "major_war_count": 0.000151,
      "famine_wave_count": 136,
      "epidemic_wave_count": 1,
      "migration_rate_t": 0.003579
    },
    {
      "year": -4450,
      "world_pop_total": 92295383.000000,
      "world_food_adequacy_index": 0.996244,
      "world_trade_intensity": 0.000705,
      "world_urban_share_proxy": 0.026630,
      "world_tech_capability_index_median": 0.409050,
      "world_state_capacity_index_median": 0.890047,
      "major_war_count": 0.000173,
      "famine_wave_count": 158,
      "epidemic_wave_count": 0,
      "migration_rate_t": 0.003756
    },
    {
      "year": -4400,
      "world_pop_total": 99195878.000000,
      "world_food_adequacy_index": 0.986578,
      "world_trade_intensity": 0.000826,
      "world_urban_share_proxy": 0.027385,
      "world_tech_capability_index_median": 0.422902,
      "world_state_capacity_index_median": 0.890566,
      "major_war_count": 0.000666,
      "famine_wave_count": 159,
      "epidemic_wave_count": 0,
      "migration_rate_t": 0.013422
    },
    {
      "year": -4350,
      "world_pop_total": 108756025.000000,
      "world_food_adequacy_index": 0.978722,
      "world_trade_intensity": 0.000565,
      "world_urban_share_proxy": 0.027822,
      "world_tech_capability_index_median": 0.436938,
      "world_state_capacity_index_median": 0.890035,
      "major_war_count": 0.001157,
      "famine_wave_count": 187,
      "epidemic_wave_count": 0,
      "migration_rate_t": 0.021278
    },
    {
      "year": -4300,
      "world_pop_total": 115986857.000000,
      "world_food_adequacy_index": 0.967549,
      "world_trade_intensity": 0.000435,
      "world_urban_share_proxy": 0.028674,
      "world_tech_capability_index_median": 0.450647,
      "world_state_capacity_index_median": 0.889364,
      "major_war_count": 0.001882,
      "famine_wave_count": 204,
      "epidemic_wave_count": 0,
      "migration_rate_t": 0.032451
    },
    {
      "year": -4250,
      "world_pop_total": 126490389.000000,
      "world_food_adequacy_index": 0.978399,
      "world_trade_intensity": 0.000434,
      "world_urban_share_proxy": 0.029923,
      "world_tech_capability_index_median": 0.465419,
      "world_state_capacity_index_median": 0.890855,
      "major_war_count": 0.001366,
      "famine_wave_count": 191,
      "epidemic_wave_count": 0,
      "migration_rate_t": 0.021601
    },
    {
      "year": -4200,
      "world_pop_total": 136532050.000000,
      "world_food_adequacy_index": 0.973868,
      "world_trade_intensity": 0.000579,
      "world_urban_share_proxy": 0.031081,
      "world_tech_capability_index_median": 0.479921,
      "world_state_capacity_index_median": 0.889109,
      "major_war_count": 0.001784,
      "famine_wave_count": 189,
      "epidemic_wave_count": 0,
      "migration_rate_t": 0.026132
    },
    {
      "year": -4150,
      "world_pop_total": 147816834.000000,
      "world_food_adequacy_index": 0.950709,
      "world_trade_intensity": 0.000549,
      "world_urban_share_proxy": 0.032094,
      "world_tech_capability_index_median": 0.493581,
      "world_state_capacity_index_median": 0.886313,
      "major_war_count": 0.003643,
      "famine_wave_count": 216,
      "epidemic_wave_count": 0,
      "migration_rate_t": 0.049291
    },
    {
      "year": -4100,
      "world_pop_total": 162174189.000000,
      "world_food_adequacy_index": 0.921038,
      "world_trade_intensity": 0.000528,
      "world_urban_share_proxy": 0.033521,
      "world_tech_capability_index_median": 0.508507,
      "world_state_capacity_index_median": 0.888195,
      "major_war_count": 0.006403,
      "famine_wave_count": 191,
      "epidemic_wave_count": 0,
      "migration_rate_t": 0.078962
    },
    {
      "year": -4050,
      "world_pop_total": 175739163.000000,
      "world_food_adequacy_index": 0.910546,
      "world_trade_intensity": 0.000421,
      "world_urban_share_proxy": 0.034977,
      "world_tech_capability_index_median": 0.524014,
      "world_state_capacity_index_median": 0.890514,
      "major_war_count": 0.007860,
      "famine_wave_count": 211,
      "epidemic_wave_count": 0,
      "migration_rate_t": 0.089454
    },
    {
      "year": -4000,
      "world_pop_total": 194460155.000000,
      "world_food_adequacy_index": 0.934863,
      "world_trade_intensity": 0.000565,
      "world_urban_share_proxy": 0.036724,
      "world_tech_capability_index_median": 0.539053,
      "world_state_capacity_index_median": 0.890366,
      "major_war_count": 0.006333,
      "famine_wave_count": 180,
      "epidemic_wave_count": 0,
      "migration_rate_t": 0.065137
    },
    {
      "year": -3950,
      "world_pop_total": 213567040.000000,
      "world_food_adequacy_index": 0.951340,
      "world_trade_intensity": 0.000583,
      "world_urban_share_proxy": 0.038522,
      "world_tech_capability_index_median": 0.554043,
      "world_state_capacity_index_median": 0.891122,
      "major_war_count": 0.005196,
      "famine_wave_count": 194,
      "epidemic_wave_count": 0,
      "migration_rate_t": 0.048660
    },
    {
      "year": -3900,
      "world_pop_total": 232609727.000000,
      "world_food_adequacy_index": 0.950809,
      "world_trade_intensity": 0.000640,
      "world_urban_share_proxy": 0.039451,
      "world_tech_capability_index_median": 0.568354,
      "world_state_capacity_index_median": 0.890729,
      "major_war_count": 0.005721,
      "famine_wave_count": 204,
      "epidemic_wave_count": 0,
      "migration_rate_t": 0.049191
    },
    {
      "year": -3850,
      "world_pop_total": 256569557.000000,
      "world_food_adequacy_index": 0.957557,
      "world_trade_intensity": 0.000798,
      "world_urban_share_proxy": 0.043560,
      "world_tech_capability_index_median": 0.582293,
      "world_state_capacity_index_median": 0.890731,
      "major_war_count": 0.005445,
      "famine_wave_count": 196,
      "epidemic_wave_count": 0,
      "migration_rate_t": 0.042443
    },
    {
      "year": -3800,
      "world_pop_total": 283658190.000000,
      "world_food_adequacy_index": 0.948491,
      "world_trade_intensity": 0.000908,
      "world_urban_share_proxy": 0.046684,
      "world_tech_capability_index_median": 0.595188,
      "world_state_capacity_index_median": 0.891299,
      "major_war_count": 0.007306,
      "famine_wave_count": 215,
      "epidemic_wave_count": 0,
      "migration_rate_t": 0.051509
    },
    {
      "year": -3750,
      "world_pop_total": 315106531.000000,
      "world_food_adequacy_index": 0.979353,
      "world_trade_intensity": 0.000541,
      "world_urban_share_proxy": 0.050202,
      "world_tech_capability_index_median": 0.610007,
      "world_state_capacity_index_median": 0.891267,
      "major_war_count": 0.003253,
      "famine_wave_count": 186,
      "epidemic_wave_count": 0,
      "migration_rate_t": 0.020647
    },
    {
      "year": -3700,
      "world_pop_total": 349832289.000000,
      "world_food_adequacy_index": 0.988875,
      "world_trade_intensity": 0.000643,
      "world_urban_share_proxy": 0.054357,
      "world_tech_capability_index_median": 0.625338,
      "world_state_capacity_index_median": 0.891312,
      "major_war_count": 0.001946,
      "famine_wave_count": 185,
      "epidemic_wave_count": 0,
      "migration_rate_t": 0.011125
    },
    {
      "year": -3650,
      "world_pop_total": 386692151.000000,
      "world_food_adequacy_index": 0.991807,
      "world_trade_intensity": 0.000924,
      "world_urban_share_proxy": 0.059775,
      "world_tech_capability_index_median": 0.639664,
      "world_state_capacity_index_median": 0.891917,
      "major_war_count": 0.001584,
      "famine_wave_count": 201,
      "epidemic_wave_count": 0,
      "migration_rate_t": 0.008193
    },
    {
      "year": -3600,
      "world_pop_total": 427165760.000000,
      "world_food_adequacy_index": 0.989319,
      "world_trade_intensity": 0.000749,
      "world_urban_share_proxy": 0.065984,
      "world_tech_capability_index_median": 0.653743,
      "world_state_capacity_index_median": 0.888772,
      "major_war_count": 0.002281,
      "famine_wave_count": 221,
      "epidemic_wave_count": 0,
      "migration_rate_t": 0.010681
    },
    {
      "year": -3550,
      "world_pop_total": 472995110.000000,
      "world_food_adequacy_index": 0.982997,
      "world_trade_intensity": 0.000458,
      "world_urban_share_proxy": 0.074112,
      "world_tech_capability_index_median": 0.670333,
      "world_state_capacity_index_median": 0.890361,
      "major_war_count": 0.004021,
      "famine_wave_count": 203,
      "epidemic_wave_count": 0,
      "migration_rate_t": 0.017003
    },
    {
      "year": -3500,
      "world_pop_total": 517241962.000000,
      "world_food_adequacy_index": 0.969432,
      "world_trade_intensity": 0.000504,
      "world_urban_share_proxy": 0.080292,
      "world_tech_capability_index_median": 0.686920,
      "world_state_capacity_index_median": 0.890016,
      "major_war_count": 0.007905,
      "famine_wave_count": 208,
      "epidemic_wave_count": 0,
      "migration_rate_t": 0.030568
    },
    {
      "year": -3450,
      "world_pop_total": 569742445.000000,
      "world_food_adequacy_index": 0.977334,
      "world_trade_intensity": 0.000507,
      "world_urban_share_proxy": 0.089078,
      "world_tech_capability_index_median": 0.701286,
      "world_state_capacity_index_median": 0.890378,
      "major_war_count": 0.006457,
      "famine_wave_count": 206,
      "epidemic_wave_count": 0,
      "migration_rate_t": 0.022666
    },
    {
      "year": -3400,
      "world_pop_total": 630235437.000000,
      "world_food_adequacy_index": 0.974238,
      "world_trade_intensity": 0.000597,
      "world_urban_share_proxy": 0.101300,
      "world_tech_capability_index_median": 0.720779,
      "world_state_capacity_index_median": 0.891073,
      "major_war_count": 0.008118,
      "famine_wave_count": 196,
      "epidemic_wave_count": 0,
      "migration_rate_t": 0.025762
    },
    {
      "year": -3350,
      "world_pop_total": 695273063.000000,
      "world_food_adequacy_index": 0.965446,
      "world_trade_intensity": 0.000622,
      "world_urban_share_proxy": 0.116845,
      "world_tech_capability_index_median": 0.733687,
      "world_state_capacity_index_median": 0.890741,
      "major_war_count": 0.012012,
      "famine_wave_count": 231,
      "epidemic_wave_count": 0,
      "migration_rate_t": 0.034554
    },
    {
      "year": -3300,
      "world_pop_total": 764134511.000000,
      "world_food_adequacy_index": 0.930477,
      "world_trade_intensity": 0.000516,
      "world_urban_share_proxy": 0.130291,
      "world_tech_capability_index_median": 0.749987,
      "world_state_capacity_index_median": 0.888624,
      "major_war_count": 0.026562,
      "famine_wave_count": 222,
      "epidemic_wave_count": 0,
      "migration_rate_t": 0.069523
    },
    {
      "year": -3250,
      "world_pop_total": 828294951.000000,
      "world_food_adequacy_index": 0.904007,
      "world_trade_intensity": 0.000458,
      "world_urban_share_proxy": 0.138795,
      "world_tech_capability_index_median": 0.765227,
      "world_state_capacity_index_median": 0.888410,
      "major_war_count": 0.039755,
      "famine_wave_count": 224,
      "epidemic_wave_count": 0,
      "migration_rate_t": 0.095993
    },
    {
      "year": -3200,
      "world_pop_total": 887947027.000000,
      "world_food_adequacy_index": 0.898955,
      "world_trade_intensity": 0.000244,
      "world_urban_share_proxy": 0.145211,
      "world_tech_capability_index_median": 0.781946,
      "world_state_capacity_index_median": 0.890649,
      "major_war_count": 0.044861,
      "famine_wave_count": 232,
      "epidemic_wave_count": 0,
      "migration_rate_t": 0.101045
    },
    {
      "year": -3150,
      "world_pop_total": 943602082.000000,
      "world_food_adequacy_index": 0.918832,
      "world_trade_intensity": 0.000574,
      "world_urban_share_proxy": 0.152120,
      "world_tech_capability_index_median": 0.798530,
      "world_state_capacity_index_median": 0.890495,
      "major_war_count": 0.038295,
      "famine_wave_count": 237,
      "epidemic_wave_count": 0,
      "migration_rate_t": 0.081168
    },
    {
      "year": -3100,
      "world_pop_total": 976778704.000000,
      "world_food_adequacy_index": 0.930009,
      "world_trade_intensity": 0.000394,
      "world_urban_share_proxy": 0.155014,
      "world_tech_capability_index_median": 0.815699,
      "world_state_capacity_index_median": 0.890381,
      "major_war_count": 0.034183,
      "famine_wave_count": 234,
      "epidemic_wave_count": 0,
      "migration_rate_t": 0.069991
    },
    {
      "year": -3050,
      "world_pop_total": 1017275252.000000,
      "world_food_adequacy_index": 0.935895,
      "world_trade_intensity": 0.000380,
      "world_urban_share_proxy": 0.158077,
      "world_tech_capability_index_median": 0.830481,
      "world_state_capacity_index_median": 0.891861,
      "major_war_count": 0.032606,
      "famine_wave_count": 256,
      "epidemic_wave_count": 0,
      "migration_rate_t": 0.064105
    },
    {
      "year": -3000,
      "world_pop_total": 1064084315.000000,
      "world_food_adequacy_index": 0.925766,
      "world_trade_intensity": 0.000420,
      "world_urban_share_proxy": 0.160188,
      "world_tech_capability_index_median": 0.843866,
      "world_state_capacity_index_median": 0.889861,
      "major_war_count": 0.039495,
      "famine_wave_count": 237,
      "epidemic_wave_count": 0,
      "migration_rate_t": 0.074234
    },
    {
      "year": -2950,
      "world_pop_total": 1120504095.000000,
      "world_food_adequacy_index": 0.939366,
      "world_trade_intensity": 0.000179,
      "world_urban_share_proxy": 0.163342,
      "world_tech_capability_index_median": 0.859023,
      "world_state_capacity_index_median": 0.890500,
      "major_war_count": 0.033971,
      "famine_wave_count": 256,
      "epidemic_wave_count": 0,
      "migration_rate_t": 0.060634
    },
    {
      "year": -2900,
      "world_pop_total": 1179257507.000000,
      "world_food_adequacy_index": 0.967042,
      "world_trade_intensity": 0.000548,
      "world_urban_share_proxy": 0.169417,
      "world_tech_capability_index_median": 0.876697,
      "world_state_capacity_index_median": 0.892358,
      "major_war_count": 0.019433,
      "famine_wave_count": 242,
      "epidemic_wave_count": 0,
      "migration_rate_t": 0.032958
    },
    {
      "year": -2850,
      "world_pop_total": 1237017175.000000,
      "world_food_adequacy_index": 0.982200,
      "world_trade_intensity": 0.001333,
      "world_urban_share_proxy": 0.176026,
      "world_tech_capability_index_median": 0.891043,
      "world_state_capacity_index_median": 0.891343,
      "major_war_count": 0.011009,
      "famine_wave_count": 280,
      "epidemic_wave_count": 0,
      "migration_rate_t": 0.017800
    },
    {
      "year": -2800,
      "world_pop_total": 1278932587.000000,
      "world_food_adequacy_index": 0.981414,
      "world_trade_intensity": 0.000883,
      "world_urban_share_proxy": 0.179990,
      "world_tech_capability_index_median": 0.904796,
      "world_state_capacity_index_median": 0.891817,
      "major_war_count": 0.011885,
      "famine_wave_count": 266,
      "epidemic_wave_count": 0,
      "migration_rate_t": 0.018586
    },
    {
      "year": -2750,
      "world_pop_total": 1311731924.000000,
      "world_food_adequacy_index": 0.971843,
      "world_trade_intensity": 0.000628,
      "world_urban_share_proxy": 0.180773,
      "world_tech_capability_index_median": 0.920886,
      "world_state_capacity_index_median": 0.890912,
      "major_war_count": 0.018467,
      "famine_wave_count": 259,
      "epidemic_wave_count": 0,
      "migration_rate_t": 0.028157
    },
    {
      "year": -2700,
      "world_pop_total": 1353460922.000000,
      "world_food_adequacy_index": 0.969325,
      "world_trade_intensity": 0.000071,
      "world_urban_share_proxy": 0.185127,
      "world_tech_capability_index_median": 0.937505,
      "world_state_capacity_index_median": 0.890466,
      "major_war_count": 0.020759,
      "famine_wave_count": 266,
      "epidemic_wave_count": 0,
      "migration_rate_t": 0.030675
    },
    {
      "year": -2650,
      "world_pop_total": 1401978857.000000,
      "world_food_adequacy_index": 0.970030,
      "world_trade_intensity": 0.000252,
      "world_urban_share_proxy": 0.190617,
      "world_tech_capability_index_median": 0.955740,
      "world_state_capacity_index_median": 0.891345,
      "major_war_count": 0.021008,
      "famine_wave_count": 263,
      "epidemic_wave_count": 0,
      "migration_rate_t": 0.029970
    },
    {
      "year": -2600,
      "world_pop_total": 1440846523.000000,
      "world_food_adequacy_index": 0.968507,
      "world_trade_intensity": 0.000436,
      "world_urban_share_proxy": 0.195375,
      "world_tech_capability_index_median": 0.967858,
      "world_state_capacity_index_median": 0.890407,
      "major_war_count": 0.022688,
      "famine_wave_count": 251,
      "epidemic_wave_count": 0,
      "migration_rate_t": 0.031493
    },
    {
      "year": -2550,
      "world_pop_total": 1461315294.000000,
      "world_food_adequacy_index": 0.971370,
      "world_trade_intensity": 0.000398,
      "world_urban_share_proxy": 0.196936,
      "world_tech_capability_index_median": 0.983511,
      "world_state_capacity_index_median": 0.890258,
      "major_war_count": 0.020919,
      "famine_wave_count": 260,
      "epidemic_wave_count": 0,
      "migration_rate_t": 0.028630
    },
    {
      "year": -2500,
      "world_pop_total": 1460905815.000000,
      "world_food_adequacy_index": 0.943463,
      "world_trade_intensity": 0.000086,
      "world_urban_share_proxy": 0.191937,
      "world_tech_capability_index_median": 0.999645,
      "world_state_capacity_index_median": 0.890038,
      "major_war_count": 0.041298,
      "famine_wave_count": 271,
      "epidemic_wave_count": 0,
      "migration_rate_t": 0.056537
    },
    {
      "year": -2450,
      "world_pop_total": 1469378574.000000,
      "world_food_adequacy_index": 0.907318,
      "world_trade_intensity": 0.000078,
      "world_urban_share_proxy": 0.192181,
      "world_tech_capability_index_median": 1.000000,
      "world_state_capacity_index_median": 0.888558,
      "major_war_count": 0.068093,
      "famine_wave_count": 265,
      "epidemic_wave_count": 0,
      "migration_rate_t": 0.092682
    },
    {
      "year": -2400,
      "world_pop_total": 1475054369.000000,
      "world_food_adequacy_index": 0.881847,
      "world_trade_intensity": 0.000155,
      "world_urban_share_proxy": 0.188736,
      "world_tech_capability_index_median": 1.000000,
      "world_state_capacity_index_median": 0.888485,
      "major_war_count": 0.087141,
      "famine_wave_count": 277,
      "epidemic_wave_count": 0,
      "migration_rate_t": 0.118153
    },
    {
      "year": -2350,
      "world_pop_total": 1500520256.000000,
      "world_food_adequacy_index": 0.909071,
      "world_trade_intensity": 0.000368,
      "world_urban_share_proxy": 0.195043,
      "world_tech_capability_index_median": 1.000000,
      "world_state_capacity_index_median": 0.891115,
      "major_war_count": 0.068220,
      "famine_wave_count": 272,
      "epidemic_wave_count": 0,
      "migration_rate_t": 0.090929
    },
    {
      "year": -2300,
      "world_pop_total": 1503217933.000000,
      "world_food_adequacy_index": 0.923489,
      "world_trade_intensity": 0.000333,
      "world_urban_share_proxy": 0.197257,
      "world_tech_capability_index_median": 1.000000,
      "world_state_capacity_index_median": 0.892696,
      "major_war_count": 0.057507,
      "famine_wave_count": 243,
      "epidemic_wave_count": 0,
      "migration_rate_t": 0.076511
    },
    {
      "year": -2250,
      "world_pop_total": 1500661532.000000,
      "world_food_adequacy_index": 0.926688,
      "world_trade_intensity": 0.000690,
      "world_urban_share_proxy": 0.196800,
      "world_tech_capability_index_median": 1.000000,
      "world_state_capacity_index_median": 0.890121,
      "major_war_count": 0.055008,
      "famine_wave_count": 297,
      "epidemic_wave_count": 0,
      "migration_rate_t": 0.073312
    },
    {
      "year": -2200,
      "world_pop_total": 1497257329.000000,
      "world_food_adequacy_index": 0.920517,
      "world_trade_intensity": 0.000168,
      "world_urban_share_proxy": 0.194759,
      "world_tech_capability_index_median": 1.000000,
      "world_state_capacity_index_median": 0.891342,
      "major_war_count": 0.059503,
      "famine_wave_count": 247,
      "epidemic_wave_count": 0,
      "migration_rate_t": 0.079483
    },
    {
      "year": -2150,
      "world_pop_total": 1513990953.000000,
      "world_food_adequacy_index": 0.911049,
      "world_trade_intensity": 0.000257,
      "world_urban_share_proxy": 0.199517,
      "world_tech_capability_index_median": 1.000000,
      "world_state_capacity_index_median": 0.890163,
      "major_war_count": 0.067335,
      "famine_wave_count": 288,
      "epidemic_wave_count": 0,
      "migration_rate_t": 0.088951
    },
    {
      "year": -2100,
      "world_pop_total": 1517170235.000000,
      "world_food_adequacy_index": 0.927347,
      "world_trade_intensity": 0.000370,
      "world_urban_share_proxy": 0.200908,
      "world_tech_capability_index_median": 1.000000,
      "world_state_capacity_index_median": 0.890523,
      "major_war_count": 0.055113,
      "famine_wave_count": 279,
      "epidemic_wave_count": 0,
      "migration_rate_t": 0.072653
    },
    {
      "year": -2050,
      "world_pop_total": 1529050547.000000,
      "world_food_adequacy_index": 0.962193,
      "world_trade_intensity": 0.000732,
      "world_urban_share_proxy": 0.206101,
      "world_tech_capability_index_median": 1.000000,
      "world_state_capacity_index_median": 0.892314,
      "major_war_count": 0.028904,
      "famine_wave_count": 238,
      "epidemic_wave_count": 0,
      "migration_rate_t": 0.037807
    },
    {
      "year": -2000,
      "world_pop_total": 1525907078.000000,
      "world_food_adequacy_index": 0.971156,
      "world_trade_intensity": 0.001700,
      "world_urban_share_proxy": 0.206064,
      "world_tech_capability_index_median": 1.000000,
      "world_state_capacity_index_median": 0.892319,
      "major_war_count": 0.022007,
      "famine_wave_count": 281,
      "epidemic_wave_count": 0,
      "migration_rate_t": 0.028844
    },
    {
      "year": -1950,
      "world_pop_total": 1518286934.000000,
      "world_food_adequacy_index": 0.979676,
      "world_trade_intensity": 0.000827,
      "world_urban_share_proxy": 0.205256,
      "world_tech_capability_index_median": 1.000000,
      "world_state_capacity_index_median": 0.891860,
      "major_war_count": 0.015429,
      "famine_wave_count": 278,
      "epidemic_wave_count": 0,
      "migration_rate_t": 0.020324
    },
    {
      "year": -1900,
      "world_pop_total": 1509516430.000000,
      "world_food_adequacy_index": 0.964998,
      "world_trade_intensity": 0.000575,
      "world_urban_share_proxy": 0.206461,
      "world_tech_capability_index_median": 1.000000,
      "world_state_capacity_index_median": 0.888738,
      "major_war_count": 0.026418,
      "famine_wave_count": 278,
      "epidemic_wave_count": 0,
      "migration_rate_t": 0.035002
    },
    {
      "year": -1850,
      "world_pop_total": 1521629782.000000,
      "world_food_adequacy_index": 0.965227,
      "world_trade_intensity": 0.000184,
      "world_urban_share_proxy": 0.206918,
      "world_tech_capability_index_median": 1.000000,
      "world_state_capacity_index_median": 0.889087,
      "major_war_count": 0.026456,
      "famine_wave_count": 280,
      "epidemic_wave_count": 0,
      "migration_rate_t": 0.034773
    },
    {
      "year": -1800,
      "world_pop_total": 1528632641.000000,
      "world_food_adequacy_index": 0.965566,
      "world_trade_intensity": 0.000241,
      "world_urban_share_proxy": 0.207151,
      "world_tech_capability_index_median": 1.000000,
      "world_state_capacity_index_median": 0.891442,
      "major_war_count": 0.026319,
      "famine_wave_count": 270,
      "epidemic_wave_count": 0,
      "migration_rate_t": 0.034434
    },
    {
      "year": -1750,
      "world_pop_total": 1520610059.000000,
      "world_food_adequacy_index": 0.961435,
      "world_trade_intensity": 0.000253,
      "world_urban_share_proxy": 0.206881,
      "world_tech_capability_index_median": 1.000000,
      "world_state_capacity_index_median": 0.891333,
      "major_war_count": 0.029321,
      "famine_wave_count": 293,
      "epidemic_wave_count": 0,
      "migration_rate_t": 0.038565
    },
    {
      "year": -1700,
      "world_pop_total": 1518502253.000000,
      "world_food_adequacy_index": 0.963906,
      "world_trade_intensity": 0.000269,
      "world_urban_share_proxy": 0.205240,
      "world_tech_capability_index_median": 1.000000,
      "world_state_capacity_index_median": 0.890805,
      "major_war_count": 0.027404,
      "famine_wave_count": 256,
      "epidemic_wave_count": 0,
      "migration_rate_t": 0.036094
    },
    {
      "year": -1650,
      "world_pop_total": 1507229447.000000,
      "world_food_adequacy_index": 0.935174,
      "world_trade_intensity": 0.000159,
      "world_urban_share_proxy": 0.200463,
      "world_tech_capability_index_median": 1.000000,
      "world_state_capacity_index_median": 0.890371,
      "major_war_count": 0.048854,
      "famine_wave_count": 283,
      "epidemic_wave_count": 0,
      "migration_rate_t": 0.064826
    },
    {
      "year": -1600,
      "world_pop_total": 1498785663.000000,
      "world_food_adequacy_index": 0.907848,
      "world_trade_intensity": 0.000471,
      "world_urban_share_proxy": 0.196063,
      "world_tech_capability_index_median": 1.000000,
      "world_state_capacity_index_median": 0.888998,
      "major_war_count": 0.069058,
      "famine_wave_count": 281,
      "epidemic_wave_count": 0,
      "migration_rate_t": 0.092152
    },
    {
      "year": -1550,
      "world_pop_total": 1501489613.000000,
      "world_food_adequacy_index": 0.886663,
      "world_trade_intensity": 0.000135,
      "world_urban_share_proxy": 0.195669,
      "world_tech_capability_index_median": 1.000000,
      "world_state_capacity_index_median": 0.890250,
      "major_war_count": 0.085088,
      "famine_wave_count": 260,
      "epidemic_wave_count": 0,
      "migration_rate_t": 0.113337
    },
    {
      "year": -1500,
      "world_pop_total": 1520767162.000000,
      "world_food_adequacy_index": 0.912770,
      "world_trade_intensity": 0.000692,
      "world_urban_share_proxy": 0.200026,
      "world_tech_capability_index_median": 1.000000,
      "world_state_capacity_index_median": 0.891318,
      "major_war_count": 0.066328,
      "famine_wave_count": 243,
      "epidemic_wave_count": 0,
      "migration_rate_t": 0.087230
    },
    {
      "year": -1450,
      "world_pop_total": 1523863178.000000,
      "world_food_adequacy_index": 0.923075,
      "world_trade_intensity": 0.000424,
      "world_urban_share_proxy": 0.204343,
      "world_tech_capability_index_median": 1.000000,
      "world_state_capacity_index_median": 0.890689,
      "major_war_count": 0.058612,
      "famine_wave_count": 266,
      "epidemic_wave_count": 0,
      "migration_rate_t": 0.076925
    },
    {
      "year": -1400,
      "world_pop_total": 1518438107.000000,
      "world_food_adequacy_index": 0.914384,
      "world_trade_intensity": 0.000457,
      "world_urban_share_proxy": 0.200802,
      "world_tech_capability_index_median": 1.000000,
      "world_state_capacity_index_median": 0.890477,
      "major_war_count": 0.065002,
      "famine_wave_count": 269,
      "epidemic_wave_count": 0,
      "migration_rate_t": 0.085616
    },
    {
      "year": -1350,
      "world_pop_total": 1514724693.000000,
      "world_food_adequacy_index": 0.913139,
      "world_trade_intensity": 0.000284,
      "world_urban_share_proxy": 0.200766,
      "world_tech_capability_index_median": 1.000000,
      "world_state_capacity_index_median": 0.890101,
      "major_war_count": 0.065785,
      "famine_wave_count": 280,
      "epidemic_wave_count": 0,
      "migration_rate_t": 0.086861
    },
    {
      "year": -1300,
      "world_pop_total": 1530240791.000000,
      "world_food_adequacy_index": 0.904029,
      "world_trade_intensity": 0.000665,
      "world_urban_share_proxy": 0.202332,
      "world_tech_capability_index_median": 1.000000,
      "world_state_capacity_index_median": 0.891480,
      "major_war_count": 0.073430,
      "famine_wave_count": 271,
      "epidemic_wave_count": 0,
      "migration_rate_t": 0.095971
    },
    {
      "year": -1250,
      "world_pop_total": 1544332290.000000,
      "world_food_adequacy_index": 0.924264,
      "world_trade_intensity": 0.000443,
      "world_urban_share_proxy": 0.207125,
      "world_tech_capability_index_median": 1.000000,
      "world_state_capacity_index_median": 0.891138,
      "major_war_count": 0.058480,
      "famine_wave_count": 246,
      "epidemic_wave_count": 0,
      "migration_rate_t": 0.075736
    },
    {
      "year": -1200,
      "world_pop_total": 1537137722.000000,
      "world_food_adequacy_index": 0.964662,
      "world_trade_intensity": 0.001290,
      "world_urban_share_proxy": 0.207998,
      "world_tech_capability_index_median": 1.000000,
      "world_state_capacity_index_median": 0.891505,
      "major_war_count": 0.027159,
      "famine_wave_count": 264,
      "epidemic_wave_count": 0,
      "migration_rate_t": 0.035338
    },
    {
      "year": -1150,
      "world_pop_total": 1515497313.000000,
      "world_food_adequacy_index": 0.980276,
      "world_trade_intensity": 0.000745,
      "world_urban_share_proxy": 0.210943,
      "world_tech_capability_index_median": 1.000000,
      "world_state_capacity_index_median": 0.892820,
      "major_war_count": 0.014946,
      "famine_wave_count": 265,
      "epidemic_wave_count": 0,
      "migration_rate_t": 0.019724
    },
    {
      "year": -1100,
      "world_pop_total": 1506107918.000000,
      "world_food_adequacy_index": 0.971872,
      "world_trade_intensity": 0.001180,
      "world_urban_share_proxy": 0.208835,
      "world_tech_capability_index_median": 1.000000,
      "world_state_capacity_index_median": 0.891307,
      "major_war_count": 0.021182,
      "famine_wave_count": 274,
      "epidemic_wave_count": 0,
      "migration_rate_t": 0.028128
    },
    {
      "year": -1050,
      "world_pop_total": 1498152634.000000,
      "world_food_adequacy_index": 0.968758,
      "world_trade_intensity": 0.000562,
      "world_urban_share_proxy": 0.208419,
      "world_tech_capability_index_median": 1.000000,
      "world_state_capacity_index_median": 0.890565,
      "major_war_count": 0.023403,
      "famine_wave_count": 262,
      "epidemic_wave_count": 0,
      "migration_rate_t": 0.031242
    },
    {
      "year": -1000,
      "world_pop_total": 1515877638.000000,
      "world_food_adequacy_index": 0.963909,
      "world_trade_intensity": 0.000170,
      "world_urban_share_proxy": 0.210074,
      "world_tech_capability_index_median": 1.000000,
      "world_state_capacity_index_median": 0.890435,
      "major_war_count": 0.027355,
      "famine_wave_count": 274,
      "epidemic_wave_count": 0,
      "migration_rate_t": 0.036091
    },
    {
      "year": -950,
      "world_pop_total": 1531191365.000000,
      "world_food_adequacy_index": 0.970677,
      "world_trade_intensity": 0.000755,
      "world_urban_share_proxy": 0.210965,
      "world_tech_capability_index_median": 1.000000,
      "world_state_capacity_index_median": 0.891645,
      "major_war_count": 0.022449,
      "famine_wave_count": 266,
      "epidemic_wave_count": 0,
      "migration_rate_t": 0.029323
    },
    {
      "year": -900,
      "world_pop_total": 1523695497.000000,
      "world_food_adequacy_index": 0.970783,
      "world_trade_intensity": 0.000706,
      "world_urban_share_proxy": 0.208871,
      "world_tech_capability_index_median": 1.000000,
      "world_state_capacity_index_median": 0.891146,
      "major_war_count": 0.022259,
      "famine_wave_count": 258,
      "epidemic_wave_count": 0,
      "migration_rate_t": 0.029217
    },
    {
      "year": -850,
      "world_pop_total": 1507364002.000000,
      "world_food_adequacy_index": 0.961606,
      "world_trade_intensity": 0.000318,
      "world_urban_share_proxy": 0.209268,
      "world_tech_capability_index_median": 1.000000,
      "world_state_capacity_index_median": 0.889145,
      "major_war_count": 0.028937,
      "famine_wave_count": 275,
      "epidemic_wave_count": 0,
      "migration_rate_t": 0.038394
    },
    {
      "year": -800,
      "world_pop_total": 1500077504.000000,
      "world_food_adequacy_index": 0.922135,
      "world_trade_intensity": 0.000256,
      "world_urban_share_proxy": 0.205644,
      "world_tech_capability_index_median": 1.000000,
      "world_state_capacity_index_median": 0.890057,
      "major_war_count": 0.058402,
      "famine_wave_count": 254,
      "epidemic_wave_count": 0,
      "migration_rate_t": 0.077865
    },
    {
      "year": -750,
      "world_pop_total": 1505343851.000000,
      "world_food_adequacy_index": 0.890235,
      "world_trade_intensity": 0.000319,
      "world_urban_share_proxy": 0.202210,
      "world_tech_capability_index_median": 1.000000,
      "world_state_capacity_index_median": 0.889730,
      "major_war_count": 0.082617,
      "famine_wave_count": 280,
      "epidemic_wave_count": 0,
      "migration_rate_t": 0.109765
    },
    {
      "year": -700,
      "world_pop_total": 1525682281.000000,
      "world_food_adequacy_index": 0.910620,
      "world_trade_intensity": 0.000525,
      "world_urban_share_proxy": 0.205602,
      "world_tech_capability_index_median": 1.000000,
      "world_state_capacity_index_median": 0.889861,
      "major_war_count": 0.068183,
      "famine_wave_count": 264,
      "epidemic_wave_count": 0,
      "migration_rate_t": 0.089380
    },
    {
      "year": -650,
      "world_pop_total": 1537452987.000000,
      "world_food_adequacy_index": 0.925262,
      "world_trade_intensity": 0.000792,
      "world_urban_share_proxy": 0.208138,
      "world_tech_capability_index_median": 1.000000,
      "world_state_capacity_index_median": 0.891318,
      "major_war_count": 0.057453,
      "famine_wave_count": 246,
      "epidemic_wave_count": 0,
      "migration_rate_t": 0.074738
    },
    {
      "year": -600,
      "world_pop_total": 1525652704.000000,
      "world_food_adequacy_index": 0.936462,
      "world_trade_intensity": 0.000999,
      "world_urban_share_proxy": 0.206250,
      "world_tech_capability_index_median": 1.000000,
      "world_state_capacity_index_median": 0.891848,
      "major_war_count": 0.048468,
      "famine_wave_count": 254,
      "epidemic_wave_count": 0,
      "migration_rate_t": 0.063538
    },
    {
      "year": -550,
      "world_pop_total": 1522955260.000000,
      "world_food_adequacy_index": 0.924419,
      "world_trade_intensity": 0.000491,
      "world_urban_share_proxy": 0.207961,
      "world_tech_capability_index_median": 1.000000,
      "world_state_capacity_index_median": 0.890762,
      "major_war_count": 0.057554,
      "famine_wave_count": 287,
      "epidemic_wave_count": 0,
      "migration_rate_t": 0.075581
    },
    {
      "year": -500,
      "world_pop_total": 1536650036.000000,
      "world_food_adequacy_index": 0.901276,
      "world_trade_intensity": 0.000347,
      "world_urban_share_proxy": 0.207622,
      "world_tech_capability_index_median": 1.000000,
      "world_state_capacity_index_median": 0.888849,
      "major_war_count": 0.075852,
      "famine_wave_count": 255,
      "epidemic_wave_count": 0,
      "migration_rate_t": 0.098724
    },
    {
      "year": -450,
      "world_pop_total": 1544436892.000000,
      "world_food_adequacy_index": 0.895647,
      "world_trade_intensity": 0.000544,
      "world_urban_share_proxy": 0.206507,
      "world_tech_capability_index_median": 1.000000,
      "world_state_capacity_index_median": 0.891472,
      "major_war_count": 0.080583,
      "famine_wave_count": 271,
      "epidemic_wave_count": 0,
      "migration_rate_t": 0.104353
    },
    {
      "year": -400,
      "world_pop_total": 1557796356.000000,
      "world_food_adequacy_index": 0.942682,
      "world_trade_intensity": 0.001512,
      "world_urban_share_proxy": 0.213544,
      "world_tech_capability_index_median": 1.000000,
      "world_state_capacity_index_median": 0.891740,
      "major_war_count": 0.044645,
      "famine_wave_count": 250,
      "epidemic_wave_count": 0,
      "migration_rate_t": 0.057318
    },
    {
      "year": -350,
      "world_pop_total": 1537856439.000000,
      "world_food_adequacy_index": 0.966530,
      "world_trade_intensity": 0.001857,
      "world_urban_share_proxy": 0.213210,
      "world_tech_capability_index_median": 1.000000,
      "world_state_capacity_index_median": 0.890044,
      "major_war_count": 0.025736,
      "famine_wave_count": 273,
      "epidemic_wave_count": 0,
      "migration_rate_t": 0.033470
    },
    {
      "year": -300,
      "world_pop_total": 1515674129.000000,
      "world_food_adequacy_index": 0.971317,
      "world_trade_intensity": 0.000000,
      "world_urban_share_proxy": 0.215210,
      "world_tech_capability_index_median": 1.000000,
      "world_state_capacity_index_median": 0.890962,
      "major_war_count": 0.021737,
      "famine_wave_count": 282,
      "epidemic_wave_count": 0,
      "migration_rate_t": 0.028683
    },
    {
      "year": -250,
      "world_pop_total": 1494604396.000000,
      "world_food_adequacy_index": 0.977897,
      "world_trade_intensity": 0.001236,
      "world_urban_share_proxy": 0.213578,
      "world_tech_capability_index_median": 1.000000,
      "world_state_capacity_index_median": 0.889061,
      "major_war_count": 0.016518,
      "famine_wave_count": 292,
      "epidemic_wave_count": 0,
      "migration_rate_t": 0.022103
    },
    {
      "year": -200,
      "world_pop_total": 1511439527.000000,
      "world_food_adequacy_index": 0.960771,
      "world_trade_intensity": 0.000196,
      "world_urban_share_proxy": 0.213729,
      "world_tech_capability_index_median": 1.000000,
      "world_state_capacity_index_median": 0.889586,
      "major_war_count": 0.029646,
      "famine_wave_count": 290,
      "epidemic_wave_count": 0,
      "migration_rate_t": 0.039229
    },
    {
      "year": -150,
      "world_pop_total": 1515838088.000000,
      "world_food_adequacy_index": 0.964100,
      "world_trade_intensity": 0.001278,
      "world_urban_share_proxy": 0.214783,
      "world_tech_capability_index_median": 1.000000,
      "world_state_capacity_index_median": 0.889414,
      "major_war_count": 0.027209,
      "famine_wave_count": 279,
      "epidemic_wave_count": 0,
      "migration_rate_t": 0.035900
    },
    {
      "year": -100,
      "world_pop_total": 1519804017.000000,
      "world_food_adequacy_index": 0.972912,
      "world_trade_intensity": 0.001032,
      "world_urban_share_proxy": 0.216630,
      "world_tech_capability_index_median": 1.000000,
      "world_state_capacity_index_median": 0.893471,
      "major_war_count": 0.020584,
      "famine_wave_count": 254,
      "epidemic_wave_count": 0,
      "migration_rate_t": 0.027088
    },
    {
      "year": -50,
      "world_pop_total": 1515584683.000000,
      "world_food_adequacy_index": 0.963804,
      "world_trade_intensity": 0.000619,
      "world_urban_share_proxy": 0.215510,
      "world_tech_capability_index_median": 1.000000,
      "world_state_capacity_index_median": 0.889449,
      "major_war_count": 0.027429,
      "famine_wave_count": 279,
      "epidemic_wave_count": 0,
      "migration_rate_t": 0.036196
    },
    {
      "year": 0,
      "world_pop_total": 1498904105.000000,
      "world_food_adequacy_index": 0.954262,
      "world_trade_intensity": 0.000271,
      "world_urban_share_proxy": 0.211200,
      "world_tech_capability_index_median": 1.000000,
      "world_state_capacity_index_median": 0.891327,
      "major_war_count": 0.034279,
      "famine_wave_count": 293,
      "epidemic_wave_count": 0,
      "migration_rate_t": 0.045738
    },
    {
      "year": 50,
      "world_pop_total": 1499220066.000000,
      "world_food_adequacy_index": 0.923930,
      "world_trade_intensity": 0.000298,
      "world_urban_share_proxy": 0.208358,
      "world_tech_capability_index_median": 1.000000,
      "world_state_capacity_index_median": 0.889143,
      "major_war_count": 0.057023,
      "famine_wave_count": 293,
      "epidemic_wave_count": 0,
      "migration_rate_t": 0.076070
    },
    {
      "year": 100,
      "world_pop_total": 1507427598.000000,
      "world_food_adequacy_index": 0.910357,
      "world_trade_intensity": 0.000402,
      "world_urban_share_proxy": 0.209534,
      "world_tech_capability_index_median": 1.000000,
      "world_state_capacity_index_median": 0.890908,
      "major_war_count": 0.067565,
      "famine_wave_count": 263,
      "epidemic_wave_count": 0,
      "migration_rate_t": 0.089643
    },
    {
      "year": 150,
      "world_pop_total": 1520803344.000000,
      "world_food_adequacy_index": 0.906196,
      "world_trade_intensity": 0.000660,
      "world_urban_share_proxy": 0.210761,
      "world_tech_capability_index_median": 1.000000,
      "world_state_capacity_index_median": 0.888867,
      "major_war_count": 0.071329,
      "famine_wave_count": 264,
      "epidemic_wave_count": 0,
      "migration_rate_t": 0.093804
    },
    {
      "year": 200,
      "world_pop_total": 1525021992.000000,
      "world_food_adequacy_index": 0.932385,
      "world_trade_intensity": 0.000694,
      "world_urban_share_proxy": 0.213076,
      "world_tech_capability_index_median": 1.000000,
      "world_state_capacity_index_median": 0.888835,
      "major_war_count": 0.051557,
      "famine_wave_count": 237,
      "epidemic_wave_count": 0,
      "migration_rate_t": 0.067615
    },
    {
      "year": 250,
      "world_pop_total": 1523328793.000000,
      "world_food_adequacy_index": 0.911544,
      "world_trade_intensity": 0.000711,
      "world_urban_share_proxy": 0.212460,
      "world_tech_capability_index_median": 1.000000,
      "world_state_capacity_index_median": 0.890430,
      "major_war_count": 0.067374,
      "famine_wave_count": 295,
      "epidemic_wave_count": 0,
      "migration_rate_t": 0.088456
    },
    {
      "year": 300,
      "world_pop_total": 1527306429.000000,
      "world_food_adequacy_index": 0.902860,
      "world_trade_intensity": 0.000328,
      "world_urban_share_proxy": 0.209194,
      "world_tech_capability_index_median": 1.000000,
      "world_state_capacity_index_median": 0.890007,
      "major_war_count": 0.074181,
      "famine_wave_count": 284,
      "epidemic_wave_count": 0,
      "migration_rate_t": 0.097140
    },
    {
      "year": 350,
      "world_pop_total": 1519546323.000000,
      "world_food_adequacy_index": 0.897867,
      "world_trade_intensity": 0.000463,
      "world_urban_share_proxy": 0.209049,
      "world_tech_capability_index_median": 1.000000,
      "world_state_capacity_index_median": 0.890149,
      "major_war_count": 0.077598,
      "famine_wave_count": 283,
      "epidemic_wave_count": 0,
      "migration_rate_t": 0.102133
    },
    {
      "year": 400,
      "world_pop_total": 1533091652.000000,
      "world_food_adequacy_index": 0.925576,
      "world_trade_intensity": 0.001152,
      "world_urban_share_proxy": 0.214964,
      "world_tech_capability_index_median": 1.000000,
      "world_state_capacity_index_median": 0.893082,
      "major_war_count": 0.057049,
      "famine_wave_count": 258,
      "epidemic_wave_count": 0,
      "migration_rate_t": 0.074424
    },
    {
      "year": 450,
      "world_pop_total": 1547491194.000000,
      "world_food_adequacy_index": 0.952326,
      "world_trade_intensity": 0.001922,
      "world_urban_share_proxy": 0.219292,
      "world_tech_capability_index_median": 1.000000,
      "world_state_capacity_index_median": 0.891709,
      "major_war_count": 0.036887,
      "famine_wave_count": 253,
      "epidemic_wave_count": 0,
      "migration_rate_t": 0.047674
    },
    {
      "year": 500,
      "world_pop_total": 1542897981.000000,
      "world_food_adequacy_index": 0.969355,
      "world_trade_intensity": 0.001404,
      "world_urban_share_proxy": 0.220836,
      "world_tech_capability_index_median": 1.000000,
      "world_state_capacity_index_median": 0.890691,
      "major_war_count": 0.023641,
      "famine_wave_count": 282,
      "epidemic_wave_count": 0,
      "migration_rate_t": 0.030645
    },
    {
      "year": 550,
      "world_pop_total": 1531276341.000000,
      "world_food_adequacy_index": 0.973276,
      "world_trade_intensity": 0.000983,
      "world_urban_share_proxy": 0.220475,
      "world_tech_capability_index_median": 1.000000,
      "world_state_capacity_index_median": 0.889282,
      "major_war_count": 0.020461,
      "famine_wave_count": 297,
      "epidemic_wave_count": 0,
      "migration_rate_t": 0.026724
    },
    {
      "year": 600,
      "world_pop_total": 1543111253.000000,
      "world_food_adequacy_index": 0.963341,
      "world_trade_intensity": 0.001431,
      "world_urban_share_proxy": 0.220905,
      "world_tech_capability_index_median": 1.000000,
      "world_state_capacity_index_median": 0.889455,
      "major_war_count": 0.028284,
      "famine_wave_count": 285,
      "epidemic_wave_count": 0,
      "migration_rate_t": 0.036659
    },
    {
      "year": 650,
      "world_pop_total": 1559539470.000000,
      "world_food_adequacy_index": 0.962343,
      "world_trade_intensity": 0.001235,
      "world_urban_share_proxy": 0.221033,
      "world_tech_capability_index_median": 1.000000,
      "world_state_capacity_index_median": 0.890089,
      "major_war_count": 0.029364,
      "famine_wave_count": 278,
      "epidemic_wave_count": 0,
      "migration_rate_t": 0.037657
    },
    {
      "year": 700,
      "world_pop_total": 1578186014.000000,
      "world_food_adequacy_index": 0.956023,
      "world_trade_intensity": 0.002073,
      "world_urban_share_proxy": 0.222796,
      "world_tech_capability_index_median": 1.000000,
      "world_state_capacity_index_median": 0.889749,
      "major_war_count": 0.034702,
      "famine_wave_count": 268,
      "epidemic_wave_count": 0,
      "migration_rate_t": 0.043977
    },
    {
      "year": 750,
      "world_pop_total": 1566024360.000000,
      "world_food_adequacy_index": 0.969939,
      "world_trade_intensity": 0.000795,
      "world_urban_share_proxy": 0.221472,
      "world_tech_capability_index_median": 1.000000,
      "world_state_capacity_index_median": 0.890081,
      "major_war_count": 0.023538,
      "famine_wave_count": 298,
      "epidemic_wave_count": 0,
      "migration_rate_t": 0.030061
    },
    {
      "year": 800,
      "world_pop_total": 1535367028.000000,
      "world_food_adequacy_index": 0.961490,
      "world_trade_intensity": 0.000614,
      "world_urban_share_proxy": 0.219965,
      "world_tech_capability_index_median": 1.000000,
      "world_state_capacity_index_median": 0.889271,
      "major_war_count": 0.029563,
      "famine_wave_count": 274,
      "epidemic_wave_count": 0,
      "migration_rate_t": 0.038510
    },
    {
      "year": 850,
      "world_pop_total": 1525748095.000000,
      "world_food_adequacy_index": 0.934635,
      "world_trade_intensity": 0.000573,
      "world_urban_share_proxy": 0.218990,
      "world_tech_capability_index_median": 1.000000,
      "world_state_capacity_index_median": 0.888718,
      "major_war_count": 0.049865,
      "famine_wave_count": 273,
      "epidemic_wave_count": 0,
      "migration_rate_t": 0.065365
    },
    {
      "year": 900,
      "world_pop_total": 1524822633.000000,
      "world_food_adequacy_index": 0.915757,
      "world_trade_intensity": 0.001082,
      "world_urban_share_proxy": 0.216418,
      "world_tech_capability_index_median": 1.000000,
      "world_state_capacity_index_median": 0.888344,
      "major_war_count": 0.064228,
      "famine_wave_count": 265,
      "epidemic_wave_count": 0,
      "migration_rate_t": 0.084243
    },
    {
      "year": 950,
      "world_pop_total": 1547670828.000000,
      "world_food_adequacy_index": 0.920985,
      "world_trade_intensity": 0.000947,
      "world_urban_share_proxy": 0.218827,
      "world_tech_capability_index_median": 1.000000,
      "world_state_capacity_index_median": 0.886526,
      "major_war_count": 0.061145,
      "famine_wave_count": 283,
      "epidemic_wave_count": 0,
      "migration_rate_t": 0.079015
    },
    {
      "year": 1000,
      "world_pop_total": 1557228177.000000,
      "world_food_adequacy_index": 0.914591,
      "world_trade_intensity": 0.001050,
      "world_urban_share_proxy": 0.218708,
      "world_tech_capability_index_median": 1.000000,
      "world_state_capacity_index_median": 0.890483,
      "major_war_count": 0.066501,
      "famine_wave_count": 264,
      "epidemic_wave_count": 0,
      "migration_rate_t": 0.085409
    },
    {
      "year": 1050,
      "world_pop_total": 1559213548.000000,
      "world_food_adequacy_index": 0.927654,
      "world_trade_intensity": 0.001423,
      "world_urban_share_proxy": 0.218389,
      "world_tech_capability_index_median": 1.000000,
      "world_state_capacity_index_median": 0.890988,
      "major_war_count": 0.056402,
      "famine_wave_count": 281,
      "epidemic_wave_count": 0,
      "migration_rate_t": 0.072346
    },
    {
      "year": 1100,
      "world_pop_total": 1533105587.000000,
      "world_food_adequacy_index": 0.914578,
      "world_trade_intensity": 0.001304,
      "world_urban_share_proxy": 0.216697,
      "world_tech_capability_index_median": 1.000000,
      "world_state_capacity_index_median": 0.887072,
      "major_war_count": 0.065480,
      "famine_wave_count": 288,
      "epidemic_wave_count": 0,
      "migration_rate_t": 0.085422
    },
    {
      "year": 1150,
      "world_pop_total": 1519235041.000000,
      "world_food_adequacy_index": 0.899939,
      "world_trade_intensity": 0.001784,
      "world_urban_share_proxy": 0.211245,
      "world_tech_capability_index_median": 1.000000,
      "world_state_capacity_index_median": 0.889508,
      "major_war_count": 0.076008,
      "famine_wave_count": 287,
      "epidemic_wave_count": 0,
      "migration_rate_t": 0.100061
    },
    {
      "year": 1200,
      "world_pop_total": 1533167044.000000,
      "world_food_adequacy_index": 0.899863,
      "world_trade_intensity": 0.002072,
      "world_urban_share_proxy": 0.216696,
      "world_tech_capability_index_median": 1.000000,
      "world_state_capacity_index_median": 0.884997,
      "major_war_count": 0.076763,
      "famine_wave_count": 286,
      "epidemic_wave_count": 0,
      "migration_rate_t": 0.100137
    },
    {
      "year": 1250,
      "world_pop_total": 1559182242.000000,
      "world_food_adequacy_index": 0.929300,
      "world_trade_intensity": 0.002314,
      "world_urban_share_proxy": 0.223252,
      "world_tech_capability_index_median": 1.000000,
      "world_state_capacity_index_median": 0.892526,
      "major_war_count": 0.055117,
      "famine_wave_count": 220,
      "epidemic_wave_count": 0,
      "migration_rate_t": 0.070700
    },
    {
      "year": 1300,
      "world_pop_total": 1558081036.000000,
      "world_food_adequacy_index": 0.953372,
      "world_trade_intensity": 0.002027,
      "world_urban_share_proxy": 0.223451,
      "world_tech_capability_index_median": 1.000000,
      "world_state_capacity_index_median": 0.889157,
      "major_war_count": 0.036325,
      "famine_wave_count": 246,
      "epidemic_wave_count": 0,
      "migration_rate_t": 0.046628
    },
    {
      "year": 1350,
      "world_pop_total": 1568079223.000000,
      "world_food_adequacy_index": 0.962143,
      "world_trade_intensity": 0.003390,
      "world_urban_share_proxy": 0.225671,
      "world_tech_capability_index_median": 1.000000,
      "world_state_capacity_index_median": 0.889719,
      "major_war_count": 0.029681,
      "famine_wave_count": 274,
      "epidemic_wave_count": 0,
      "migration_rate_t": 0.037857
    },
    {
      "year": 1400,
      "world_pop_total": 1564452770.000000,
      "world_food_adequacy_index": 0.972812,
      "world_trade_intensity": 0.001730,
      "world_urban_share_proxy": 0.226425,
      "world_tech_capability_index_median": 1.000000,
      "world_state_capacity_index_median": 0.886073,
      "major_war_count": 0.021267,
      "famine_wave_count": 265,
      "epidemic_wave_count": 0,
      "migration_rate_t": 0.027188
    },
    {
      "year": 1450,
      "world_pop_total": 1534430436.000000,
      "world_food_adequacy_index": 0.952389,
      "world_trade_intensity": 0.002255,
      "world_urban_share_proxy": 0.226844,
      "world_tech_capability_index_median": 1.000000,
      "world_state_capacity_index_median": 0.889779,
      "major_war_count": 0.036528,
      "famine_wave_count": 276,
      "epidemic_wave_count": 0,
      "migration_rate_t": 0.047611
    },
    {
      "year": 1500,
      "world_pop_total": 1545503365.000000,
      "world_food_adequacy_index": 0.959622,
      "world_trade_intensity": 0.001752,
      "world_urban_share_proxy": 0.226649,
      "world_tech_capability_index_median": 1.000000,
      "world_state_capacity_index_median": 0.889149,
      "major_war_count": 0.031202,
      "famine_wave_count": 274,
      "epidemic_wave_count": 0,
      "migration_rate_t": 0.040378
    },
    {
      "year": 1550,
      "world_pop_total": 1550917654.000000,
      "world_food_adequacy_index": 0.963227,
      "world_trade_intensity": 0.001950,
      "world_urban_share_proxy": 0.228283,
      "world_tech_capability_index_median": 1.000000,
      "world_state_capacity_index_median": 0.888968,
      "major_war_count": 0.028516,
      "famine_wave_count": 264,
      "epidemic_wave_count": 0,
      "migration_rate_t": 0.036773
    },
    {
      "year": 1600,
      "world_pop_total": 1537233095.000000,
      "world_food_adequacy_index": 0.974278,
      "world_trade_intensity": 0.002066,
      "world_urban_share_proxy": 0.226969,
      "world_tech_capability_index_median": 1.000000,
      "world_state_capacity_index_median": 0.885034,
      "major_war_count": 0.019771,
      "famine_wave_count": 261,
      "epidemic_wave_count": 0,
      "migration_rate_t": 0.025722
    },
    {
      "year": 1650,
      "world_pop_total": 1528430831.000000,
      "world_food_adequacy_index": 0.970941,
      "world_trade_intensity": 0.002193,
      "world_urban_share_proxy": 0.224752,
      "world_tech_capability_index_median": 1.000000,
      "world_state_capacity_index_median": 0.884829,
      "major_war_count": 0.022207,
      "famine_wave_count": 281,
      "epidemic_wave_count": 0,
      "migration_rate_t": 0.029059
    },
    {
      "year": 1700,
      "world_pop_total": 1529550394.000000,
      "world_food_adequacy_index": 0.936215,
      "world_trade_intensity": 0.001806,
      "world_urban_share_proxy": 0.223426,
      "world_tech_capability_index_median": 1.000000,
      "world_state_capacity_index_median": 0.883495,
      "major_war_count": 0.048781,
      "famine_wave_count": 290,
      "epidemic_wave_count": 0,
      "migration_rate_t": 0.063785
    },
    {
      "year": 1750,
      "world_pop_total": 1526606388.000000,
      "world_food_adequacy_index": 0.928656,
      "world_trade_intensity": 0.001545,
      "world_urban_share_proxy": 0.222296,
      "world_tech_capability_index_median": 1.000000,
      "world_state_capacity_index_median": 0.881616,
      "major_war_count": 0.054457,
      "famine_wave_count": 264,
      "epidemic_wave_count": 0,
      "migration_rate_t": 0.071344
    },
    {
      "year": 1800,
      "world_pop_total": 1540065043.000000,
      "world_food_adequacy_index": 0.923017,
      "world_trade_intensity": 0.001578,
      "world_urban_share_proxy": 0.223787,
      "world_tech_capability_index_median": 1.000000,
      "world_state_capacity_index_median": 0.889367,
      "major_war_count": 0.059280,
      "famine_wave_count": 266,
      "epidemic_wave_count": 0,
      "migration_rate_t": 0.076983
    },
    {
      "year": 1850,
      "world_pop_total": 1547536055.000000,
      "world_food_adequacy_index": 0.932734,
      "world_trade_intensity": 0.001387,
      "world_urban_share_proxy": 0.225861,
      "world_tech_capability_index_median": 1.000000,
      "world_state_capacity_index_median": 0.891477,
      "major_war_count": 0.052048,
      "famine_wave_count": 262,
      "epidemic_wave_count": 0,
      "migration_rate_t": 0.067266
    },
    {
      "year": 1900,
      "world_pop_total": 1547576958.000000,
      "world_food_adequacy_index": 0.915691,
      "world_trade_intensity": 0.001715,
      "world_urban_share_proxy": 0.225402,
      "world_tech_capability_index_median": 1.000000,
      "world_state_capacity_index_median": 0.887080,
      "major_war_count": 0.065238,
      "famine_wave_count": 287,
      "epidemic_wave_count": 0,
      "migration_rate_t": 0.084309
    },
    {
      "year": 1950,
      "world_pop_total": 1550814550.000000,
      "world_food_adequacy_index": 0.902488,
      "world_trade_intensity": 0.001717,
      "world_urban_share_proxy": 0.222815,
      "world_tech_capability_index_median": 1.000000,
      "world_state_capacity_index_median": 0.883131,
      "major_war_count": 0.075611,
      "famine_wave_count": 274,
      "epidemic_wave_count": 0,
      "migration_rate_t": 0.097512
    },
    {
      "year": 2000,
      "world_pop_total": 1560593033.000000,
      "world_food_adequacy_index": 0.898230,
      "world_trade_intensity": 0.001786,
      "world_urban_share_proxy": 0.221297,
      "world_tech_capability_index_median": 1.000000,
      "world_state_capacity_index_median": 0.887762,
      "major_war_count": 0.079411,
      "famine_wave_count": 277,
      "epidemic_wave_count": 0,
      "migration_rate_t": 0.101770
    },
    {
      "year": 2025,
      "world_pop_total": 1561244493.000000,
      "world_food_adequacy_index": 0.972758,
      "world_trade_intensity": 0.002350,
      "world_urban_share_proxy": 0.229520,
      "world_tech_capability_index_median": 1.000000,
      "world_state_capacity_index_median": 0.881661,
      "major_war_count": 0.010633,
      "famine_wave_count": 94,
      "epidemic_wave_count": 0,
      "migration_rate_t": 0.027242
    }
  ]
}
